bw_merge_window/__init__.py
bw_merge_window/entry.py
bw_merge_window/logger.py
bw_merge_window/merge.py
bw_merge_window-0.2.0.dist-info/LICENSE
bw_merge_window-0.2.0.dist-info/METADATA
bw_merge_window-0.2.0.dist-info/WHEEL
bw_merge_window-0.2.0.dist-info/entry_points.txt
bw_merge_window-0.2.0.dist-info/RECORD
