Metadata-Version: 2.1
Name: bw-merge-window
Version: 0.2.0
Summary: A python extension for quick access to bigWig and bigBed files.
License: GPL-3.0
Author: David Lougheed
Author-email: david.lougheed@mail.mcgill.ca
Requires-Python: >=3.10,<4.0
Classifier: License :: OSI Approved :: GNU General Public License v3 (GPLv3)
Classifier: Programming Language :: Python :: 3
Classifier: Programming Language :: Python :: 3.10
Classifier: Programming Language :: Python :: 3.11
Classifier: Programming Language :: Python :: 3.12
Requires-Dist: numpy (>=1.26.2,<2.0.0)
Requires-Dist: pybigwig (>=0.3.22,<0.4.0)
